securicad/langspec/__init__.py
securicad/langspec/lang.py
securicad/langspec/lang.schema.json
securicad/langspec/lang_types.py
securicad/langspec/py.typed
securicad/langspec/reader.py
securicad/langspec/step_types.py
securicad/langspec/ttc_types.py
securicad/model/__init__.py
securicad/model/association.py
securicad/model/attacker.py
securicad/model/attackstep.py
securicad/model/base.py
securicad/model/defense.py
securicad/model/es_serializer.py
securicad/model/exceptions.py
securicad/model/icon.py
securicad/model/json_serializer.py
securicad/model/model.py
securicad/model/model.schema.json
securicad/model/object.py
securicad/model/py.typed
securicad/model/scad_serializer.py
securicad/model/securilang_validator.py
securicad/model/utility.py
securicad/model/validator.py
securicad/model/ModelViewsPackage/ModelViewsPackage.py
securicad/model/ModelViewsPackage/__init__.py
securicad/model/ObjectModelPackage/ObjectModelPackage.py
securicad/model/ObjectModelPackage/__init__.py
securicad/model/meta/__init__.py
securicad/model/meta/attackstep.schema.json
securicad/model/meta/group.schema.json
securicad/model/meta/meta_validator.py
securicad/model/meta/model.schema.json
securicad/model/meta/object.schema.json
securicad/model/meta/view.schema.json
securicad/model/visual/__init__.py
securicad/model/visual/container.py
securicad/model/visual/exceptions.py
securicad/model/visual/group.py
securicad/model/visual/layout.py
securicad/model/visual/view.py
securicad/model/visual/viewitem.py
securicad/model/visual/viewobject.py
securicad_model-1.2.0.dist-info/LICENSE
securicad_model-1.2.0.dist-info/METADATA
securicad_model-1.2.0.dist-info/NOTICE
securicad_model-1.2.0.dist-info/WHEEL
securicad_model-1.2.0.dist-info/top_level.txt
securicad_model-1.2.0.dist-info/RECORD
